<scene version="1.1.0" shadowVolume="256 256 256">
	<environment sunBrightness="1"/>
	<body name="root1" tags="root1" dynamic="false">
		<voxbox name="b1" tags="b1" pos="-10.0 -11.7 -10.0" size="200 10 200" color="0.31 0.71 0.08"/>
		<instance pos="-3.4 -5.2 2.9" rot="0 180 0" file="MOD/assets/vehicle/car/musclecar.xml"/>
		<voxbox name="b2" tags="b2" pos="-10.0 -11.7 10.0" size="200 10 200" color="0.31 0.71 0.08"/>
		<voxbox name="b1" tags="b1" pos="-10.0 -11.7 30.0" size="200 10 800" color="0.31 0.71 0.08"/>
		<script file="main.lua"/>
		<script file="MOD/lua/cycleplayer.lua"/>
		<spawnpoint pos="0.0 7.3 0.0"/>
	</body>
</scene>

